[{"id": "", "text": "Any"},{"id":"139","text":"1292 Advanced Programmable Video System"},{"id":"50","text":"3DO Interactive Multiplayer"},{"id":"116","text":"Acorn Archimedes"},{"id":"134","text":"Acorn Electron"},{"id":"389","text":"AirConsole"},{"id":"132","text":"Amazon Fire TV"},{"id":"16","text":"Amiga"},{"id":"114","text":"Amiga CD32"},{"id":"25","text":"Amstrad CPC"},{"id":"154","text":"Amstrad PCW"},{"id":"100","text":"Analogue electronics"},{"id":"34","text":"Android"},{"id":"75","text":"Apple II"},{"id":"115","text":"Apple IIGS"},{"id":"52","text":"Arcade"},{"id":"438","text":"Arduboy"},{"id":"59","text":"Atari 2600"},{"id":"66","text":"Atari 5200"},{"id":"60","text":"Atari 7800"},{"id":"65","text":"Atari 8-bit"},{"id":"62","text":"Atari Jaguar"},{"id":"410","text":"Atari Jaguar CD"},{"id":"61","text":"Atari Lynx"},{"id":"63","text":"Atari ST/STE"},{"id":"140","text":"AY-3-8500"},{"id":"145","text":"AY-3-8603"},{"id":"146","text":"AY-3-8605"},{"id":"147","text":"AY-3-8606"},{"id":"148","text":"AY-3-8607"},{"id":"141","text":"AY-3-8610"},{"id":"144","text":"AY-3-8710"},{"id":"143","text":"AY-3-8760"},{"id":"91","text":"Bally Astrocade"},{"id":"69","text":"BBC Microcomputer System"},{"id":"73","text":"BlackBerry OS"},{"id":"239","text":"Blu-ray Player"},{"id":"107","text":"Call-A-Computer time-shared mainframe computer system"},{"id":"380","text":"Casio Loopy"},{"id":"109","text":"CDC Cyber 70"},{"id":"68","text":"ColecoVision"},{"id":"93","text":"Commodore 16"},{"id":"15","text":"Commodore C64/128/MAX"},{"id":"158","text":"Commodore CDTV"},{"id":"90","text":"Commodore PET"},{"id":"94","text":"Commodore Plus/4"},{"id":"71","text":"Commodore VIC-20"},{"id":"164","text":"Daydream"},{"id":"98","text":"DEC GT40"},{"id":"85","text":"Donner Model 30"},{"id":"13","text":"DOS"},{"id":"153","text":"Dragon 32/64"},{"id":"23","text":"Dreamcast"},{"id":"203","text":"DUPLICATE Stadia"},{"id":"238","text":"DVD Player"},{"id":"102","text":"EDSAC"},{"id":"375","text":"Epoch Cassette Vision"},{"id":"376","text":"Epoch Super Cassette Vision"},{"id":"309","text":"Evercade"},{"id":"236","text":"Exidy Sorcerer"},{"id":"127","text":"Fairchild Channel F"},{"id":"99","text":"Family Computer"},{"id":"51","text":"Family Computer Disk System"},{"id":"101","text":"Ferranti Nimrod Computer"},{"id":"152","text":"FM-7"},{"id":"118","text":"FM Towns"},{"id":"378","text":"Gamate"},{"id":"33","text":"Game Boy"},{"id":"24","text":"Game Boy Advance"},{"id":"22","text":"Game Boy Color"},{"id":"379","text":"Game.com"},{"id":"307","text":"Game & Watch"},{"id":"388","text":"Gear VR"},{"id":"170","text":"Google Stadia"},{"id":"411","text":"Handheld Electronic LCD"},{"id":"104","text":"HP 2100"},{"id":"105","text":"HP 3000"},{"id":"135","text":"Hyper Neo Geo 64"},{"id":"407","text":"HyperScan"},{"id":"111","text":"Imlac PDS-1"},{"id":"67","text":"Intellivision"},{"id":"382","text":"Intellivision Amico"},{"id":"39","text":"iOS"},{"id":"412","text":"Leapster"},{"id":"413","text":"Leapster Explorer/LeadPad Explorer"},{"id":"414","text":"LeapTV"},{"id":"409","text":"Legacy Computer"},{"id":"55","text":"Legacy Mobile Device"},{"id":"3","text":"Linux"},{"id":"14","text":"Mac"},{"id":"408","text":"Mega Duck/Cougar Boy"},{"id":"386","text":"Meta Quest 2"},{"id":"112","text":"Microcomputer"},{"id":"89","text":"Microvision"},{"id":"27","text":"MSX"},{"id":"53","text":"MSX2"},{"id":"157","text":"NEC PC-6000 Series"},{"id":"80","text":"Neo Geo AES"},{"id":"136","text":"Neo Geo CD"},{"id":"79","text":"Neo Geo MVS"},{"id":"119","text":"Neo Geo Pocket"},{"id":"120","text":"Neo Geo Pocket Color"},{"id":"137","text":"New Nintendo 3DS"},{"id":"42","text":"N-Gage"},{"id":"37","text":"Nintendo 3DS"},{"id":"4","text":"Nintendo 64"},{"id":"416","text":"Nintendo 64DD"},{"id":"20","text":"Nintendo DS"},{"id":"159","text":"Nintendo DSi"},{"id":"18","text":"Nintendo Entertainment System"},{"id":"21","text":"Nintendo GameCube"},{"id":"131","text":"Nintendo PlayStation"},{"id":"130","text":"Nintendo Switch"},{"id":"122","text":"Nuon"},{"id":"387","text":"Oculus Go"},{"id":"384","text":"Oculus Quest"},{"id":"385","text":"Oculus Rift"},{"id":"162","text":"Oculus VR"},{"id":"88","text":"Odyssey"},{"id":"133","text":"Odyssey 2 / Videopac G7000"},{"id":"113","text":"OnLive Game System"},{"id":"372","text":"OOParts"},{"id":"72","text":"Ouya"},{"id":"417","text":"Palm OS"},{"id":"142","text":"PC-50X Family"},{"id":"125","text":"PC-8801"},{"id":"149","text":"PC-98"},{"id":"128","text":"PC Engine SuperGrafx"},{"id":"274","text":"PC-FX"},{"id":"6","text":"PC (Microsoft Windows)"},{"id":"95","text":"PDP-1"},{"id":"96","text":"PDP-10"},{"id":"108","text":"PDP-11"},{"id":"103","text":"PDP-7"},{"id":"97","text":"PDP-8"},{"id":"117","text":"Philips CD-i"},{"id":"110","text":"PLATO"},{"id":"381","text":"Playdate"},{"id":"308","text":"Playdia"},{"id":"7","text":"PlayStation"},{"id":"8","text":"PlayStation 2"},{"id":"9","text":"PlayStation 3"},{"id":"48","text":"PlayStation 4"},{"id":"167","text":"PlayStation 5"},{"id":"38","text":"PlayStation Portable"},{"id":"46","text":"PlayStation Vita"},{"id":"165","text":"PlayStation VR"},{"id":"390","text":"PlayStation VR2"},{"id":"377","text":"Plug & Play"},{"id":"441","text":"PocketStation"},{"id":"166","text":"Pokémon mini"},{"id":"306","text":"Satellaview"},{"id":"106","text":"SDS Sigma 7"},{"id":"30","text":"Sega 32X"},{"id":"78","text":"Sega CD"},{"id":"35","text":"Sega Game Gear"},{"id":"64","text":"Sega Master System/Mark III"},{"id":"29","text":"Sega Mega Drive/Genesis"},{"id":"339","text":"Sega Pico"},{"id":"32","text":"Sega Saturn"},{"id":"84","text":"SG-1000"},{"id":"374","text":"Sharp MZ-2200"},{"id":"77","text":"Sharp X1"},{"id":"121","text":"Sharp X68000"},{"id":"406","text":"Sinclair QL"},{"id":"373","text":"Sinclair ZX81"},{"id":"237","text":"Sol-20"},{"id":"163","text":"SteamVR"},{"id":"58","text":"Super Famicom"},{"id":"19","text":"Super Nintendo Entertainment System"},{"id":"124","text":"SwanCrystal"},{"id":"44","text":"Tapwave Zodiac"},{"id":"155","text":"Tatung Einstein"},{"id":"129","text":"Texas Instruments TI-99"},{"id":"156","text":"Thomson MO5"},{"id":"126","text":"TRS-80"},{"id":"151","text":"TRS-80 Color Computer"},{"id":"86","text":"TurboGrafx-16/PC Engine"},{"id":"150","text":"Turbografx-16/PC Engine CD"},{"id":"138","text":"VC 4000"},{"id":"70","text":"Vectrex"},{"id":"87","text":"Virtual Boy"},{"id":"47","text":"Virtual Console"},{"id":"440","text":"Visual Memory Unit / Visual Memory System"},{"id":"439","text":"V.Smile"},{"id":"415","text":"Watara/QuickShot Supervision"},{"id":"82","text":"Web browser"},{"id":"5","text":"Wii"},{"id":"41","text":"Wii U"},{"id":"161","text":"Windows Mixed Reality"},{"id":"405","text":"Windows Mobile"},{"id":"74","text":"Windows Phone"},{"id":"57","text":"WonderSwan"},{"id":"123","text":"WonderSwan Color"},{"id":"11","text":"Xbox"},{"id":"12","text":"Xbox 360"},{"id":"49","text":"Xbox One"},{"id":"169","text":"Xbox Series X|S"},{"id":"240","text":"Zeebo"},{"id":"26","text":"ZX Spectrum"}]